Metadata-Version: 2.1
Name: outgraph
Version: 1.0.0
Summary: Outlier detection algorithm for graph datasets
Home-page: https://github.com/shobrook/outgraph
Author: shobrook
Author-email: shobrookj@gmail.com
License: MIT
Keywords: outlier-detection,outlier,graph,mahalanobis
Platform: UNKNOWN
Requires-Python: >=3
License-File: LICENSE
